LICENSE
MANIFEST.in
README.md
pyproject.toml
setup.json
setup.py
aiida_champ/__init__.py
aiida_champ/calculations.py
aiida_champ/cli.py
aiida_champ/helpers.py
aiida_champ/parsers.py
aiida_champ.egg-info/PKG-INFO
aiida_champ.egg-info/SOURCES.txt
aiida_champ.egg-info/dependency_links.txt
aiida_champ.egg-info/entry_points.txt
aiida_champ.egg-info/requires.txt
aiida_champ.egg-info/top_level.txt
aiida_champ/data/__init__.py