Metadata-Version: 2.1
Name: aiida-champ
Version: 1.2.6
Summary: AiiDA plugin that wraps the vmc executable of CHAMP code for computing the total energy and much more stuff.
Home-page: https://github.com/neelravi/aiida-champ
Author: Ravindra Shinde
Author-email: r.l.shinde@utwente.nl
License: MIT
Platform: UNKNOWN
Classifier: Programming Language :: Python
Classifier: Intended Audience :: Science/Research
Classifier: License :: OSI Approved :: MIT License
Classifier: Natural Language :: English
Classifier: Framework :: AiiDA
Provides-Extra: testing
Provides-Extra: pre-commit
Provides-Extra: docs
License-File: LICENSE
